file_sorter/__init__.py
file_sorter/sorter.py
ggfile_sorter-0.3.0.dist-info/METADATA
ggfile_sorter-0.3.0.dist-info/WHEEL
ggfile_sorter-0.3.0.dist-info/top_level.txt
ggfile_sorter-0.3.0.dist-info/RECORD
